mtg_ssm/__init__.py
mtg_ssm/_version.py
mtg_ssm/py.typed
mtg_ssm/ssm.py
mtg_ssm/containers/__init__.py
mtg_ssm/containers/bundles.py
mtg_ssm/containers/collection.py
mtg_ssm/containers/counts.py
mtg_ssm/containers/indexes.py
mtg_ssm/containers/legacy.py
mtg_ssm/mtg/__init__.py
mtg_ssm/mtg/util.py
mtg_ssm/scryfall/__init__.py
mtg_ssm/scryfall/fetcher.py
mtg_ssm/scryfall/models.py
mtg_ssm/serialization/__init__.py
mtg_ssm/serialization/csv_serializer.py
mtg_ssm/serialization/interface.py
mtg_ssm/serialization/xlsx_serializer.py
mtg_ssm-2.7.0.dist-info/LICENSE.txt
mtg_ssm-2.7.0.dist-info/METADATA
mtg_ssm-2.7.0.dist-info/WHEEL
mtg_ssm-2.7.0.dist-info/entry_points.txt
mtg_ssm-2.7.0.dist-info/top_level.txt
mtg_ssm-2.7.0.dist-info/RECORD
