Metadata-Version: 2.2
Name: mtg_ssm
Version: 2.7.0
Summary: A tool to manage Magic: the Gathering collection spreadsheets
Author-email: George Leslie-Waksman <waksman@gmail.com>
License: MIT
Project-URL: Homepage, https://github.com/gwax/mtg_ssm
Project-URL: Bug Tracker, https://github.com/gwax/mtg_ssm/issues
Keywords: mtg,magic,collection,tracking,spreadsheet
Classifier: Development Status :: 5 - Production/Stable
Classifier: Environment :: Console
Classifier: Intended Audience :: End Users/Desktop
Classifier: License :: OSI Approved :: MIT License
Classifier: Operating System :: MacOS
Classifier: Operating System :: Microsoft :: Windows
Classifier: Operating System :: OS Independent
Classifier: Operating System :: POSIX
Classifier: Operating System :: Unix
Classifier: Programming Language :: Python
Classifier: Programming Language :: Python :: 3
Classifier: Programming Language :: Python :: 3 :: Only
Classifier: Programming Language :: Python :: 3.9
Classifier: Programming Language :: Python :: 3.10
Classifier: Programming Language :: Python :: 3.11
Classifier: Programming Language :: Python :: 3.12
Classifier: Programming Language :: Python :: 3.13
Classifier: Topic :: Games/Entertainment
Requires-Python: >=3.9
License-File: LICENSE.txt
Requires-Dist: appdirs~=1.4
Requires-Dist: msgspec~=0.15
Requires-Dist: openpyxl~=3.1
Requires-Dist: requests~=2.27
Requires-Dist: requests-cache~=0.9.8
Requires-Dist: typing_extensions~=4.8.0
Provides-Extra: lxml
Requires-Dist: lxml>=3.7.2; extra == "lxml"
Provides-Extra: dev
Requires-Dist: black; extra == "dev"
Requires-Dist: coverage[toml]; extra == "dev"
Requires-Dist: doc8; extra == "dev"
Requires-Dist: exceptiongroup; extra == "dev"
Requires-Dist: freezegun; extra == "dev"
Requires-Dist: lxml; extra == "dev"
Requires-Dist: mypy; extra == "dev"
Requires-Dist: openpyxl-stubs; extra == "dev"
Requires-Dist: pip; extra == "dev"
Requires-Dist: Pygments; extra == "dev"
Requires-Dist: pytest>=6.0; extra == "dev"
Requires-Dist: pytest-cov; extra == "dev"
Requires-Dist: responses; extra == "dev"
Requires-Dist: ruff; extra == "dev"
Requires-Dist: setuptools>=45; extra == "dev"
Requires-Dist: setuptools-scm[toml]>=6.2; extra == "dev"
Requires-Dist: syrupy>=4.0; extra == "dev"
Requires-Dist: types-appdirs; extra == "dev"
Requires-Dist: types-freezegun; extra == "dev"
Requires-Dist: types-requests; extra == "dev"
Requires-Dist: wheel; extra == "dev"
